sentichain/__init__.py
sentichain/client.py
sentichain/keys.py
sentichain/transaction.py
sentichain-0.2.1.dist-info/licenses/LICENSE
sentichain-0.2.1.dist-info/METADATA
sentichain-0.2.1.dist-info/WHEEL
sentichain-0.2.1.dist-info/top_level.txt
sentichain-0.2.1.dist-info/RECORD
