Metadata-Version: 2.4
Name: sentichain
Version: 0.2.1
Summary: A Python client for interacting with the SentiChain
Author-email: Edward Chen <rchen@yototec.com>
License: Copyright (c) 2024-2025 SentiChain
Project-URL: Homepage, https://github.com/SentiChain/client_lightweight
Project-URL: Source Code, https://github.com/SentiChain/client_lightweight
Project-URL: Tracker, https://github.com/SentiChain/client_lightweight/issues
Keywords: sentichain,api,client
Classifier: Programming Language :: Python :: 3
Classifier: License :: OSI Approved :: MIT License
Classifier: Operating System :: OS Independent
Requires-Python: >=3.7
License-File: LICENSE
Requires-Dist: requests==2.32.3
Requires-Dist: cryptography==42.0.5
Dynamic: license-file
